Circuit Code/main.v
module jkff(input  J, K , clk ,rst, output reg Q);
  always @(negedge clk)
  begin
    if(rst)
      Q <= 1'b0;
    else 
      begin case({J,K})
        2'b00 : Q <= Q   ;
        2'b01 : Q <= 1'b0;
        2'b10 : Q <= 1'b1;
        2'b11 : Q <= ~Q  ;
      endcase
    end
  end
endmodule

module gen(input clk, rst, output [3:0] Q);
  
  wire d[1:0];
  wire c2, q;

  assign c2 = 1;
  invert i1 (Q[3], d[0]);
  invert i2 (c2, Q[0]);
  and2 a1 (Q[1], Q[2], d[1]);
  
  jkff first (1'b1, 1'b1, clk, rst, q);
  jkff second (d[0], d[0], q, rst, Q[1]);
  jkff third (1'b1, 1'b1, Q[1], rst, Q[2]);
  jkff fourth (d[1], Q[3], q, rst, Q[3]);

endmodule

Circuit Code/lib.v
module invert (input wire i, output wire o);
   assign o = !i;
endmodule

module and2 (input wire i0, i1, output wire o);
  assign o = i0 & i1;
endmodule

Circuit Code/tb.v
module TB;
  reg CLK = 0, rst = 1;
  wire[3:0] Q;
  gen g1 (CLK, rst, Q);

  initial begin 
    $dumpfile("tb_dump.vcd"); 
    $dumpvars(0, TB); 
  end
  
  initial repeat(40) #50 CLK=~CLK;
  initial #70 rst = 0;
endmodule

Circuit Code/tb_dump.vcd
$date
	Sun Nov 15 23:59:44 2020
$end
$version
	Icarus Verilog
$end
$timescale
	1s
$end
$scope module TB $end
$var wire 4 ! Q [3:0] $end
$var reg 1 " CLK $end
$var reg 1 # rst $end
$scope module g1 $end
$var wire 1 $ c2 $end
$var wire 1 " clk $end
$var wire 1 # rst $end
$var wire 1 % q $end
$var wire 4 & Q [3:0] $end
$scope module a1 $end
$var wire 1 ' i0 $end
$var wire 1 ( i1 $end
$var wire 1 ) o $end
$upscope $end
$scope module first $end
$var wire 1 * J $end
$var wire 1 + K $end
$var wire 1 " clk $end
$var wire 1 # rst $end
$var reg 1 % Q $end
$upscope $end
$scope module fourth $end
$var wire 1 ) J $end
$var wire 1 , K $end
$var wire 1 % clk $end
$var wire 1 # rst $end
$var reg 1 - Q $end
$upscope $end
$scope module i1 $end
$var wire 1 . i $end
$var wire 1 / o $end
$upscope $end
$scope module i2 $end
$var wire 1 $ i $end
$var wire 1 0 o $end
$upscope $end
$scope module second $end
$var wire 1 / J $end
$var wire 1 / K $end
$var wire 1 % clk $end
$var wire 1 # rst $end
$var reg 1 1 Q $end
$upscope $end
$scope module third $end
$var wire 1 2 J $end
$var wire 1 3 K $end
$var wire 1 4 clk $end
$var wire 1 # rst $end
$var reg 1 5 Q $end
$upscope $end
$upscope $end
$upscope $end
$enddefinitions $end
#0
$dumpvars
05
04
13
12
01
00
1/
0.
0-
0,
1+
1*
0)
0(
0'
b0 &
0%
1$
1#
0"
b0 !
$end
#50
1"
#70
0#
#100
1%
0"
#150
1"
#200
14
1'
b10 !
b10 &
11
0%
0"
#250
1"
#300
1%
0"
#350
1"
#400
1(
15
04
0'
b100 !
b100 &
01
0%
0"
#450
1"
#500
1%
0"
#550
1"
#600
1)
14
1'
b110 !
b110 &
11
0%
0"
#650
1"
#700
1%
0"
#750
1"
#800
0(
05
0)
04
0'
1,
0/
1.
01
b1000 !
b1000 &
1-
0%
0"
#850
1"
#900
1%
0"
#950
1"
#1000
0,
1/
0.
b0 !
b0 &
0-
0%
0"
#1050
1"
#1100
1%
0"
#1150
1"
#1200
14
1'
b10 !
b10 &
11
0%
0"
#1250
1"
#1300
1%
0"
#1350
1"
#1400
1(
15
04
0'
b100 !
b100 &
01
0%
0"
#1450
1"
#1500
1%
0"
#1550
1"
#1600
1)
14
1'
b110 !
b110 &
11
0%
0"
#1650
1"
#1700
1%
0"
#1750
1"
#1800
0(
05
0)
1,
0/
1.
04
0'
1-
b1000 !
b1000 &
01
0%
0"
#1850
1"
#1900
1%
0"
#1950
1"
#2000
0,
1/
0.
b0 !
b0 &
0-
0%
0"
