Algorithmic/main.v
module evencounter(input wire clock, reset, output wire [3:0] count_num);
	reg [3:0] num = 4'b0000;
	always @(posedge (clock) or posedge (reset))
	begin 
		if(reset)
			num = 4'b0000;
		else 
			num = num + 4'b0010;
	end
	assign count_num = num;
endmodule

Algorithmic/tb.v
module tb();
	reg clock, reset;
	wire [3:0] num;
	evencounter e1 (clock, reset, num);

	initial begin 
		$dumpfile("tb_dump.vcd"); 
		$dumpvars(0, tb); 
	end

	initial begin 
		clock = 1'b0; repeat(90) #10 clock =~ clock;
	end

	initial begin
		reset=1'b0;
		#310
		reset=1'b1;
		#20
		reset=1'b0;
	end
endmodule

Algorithmic/tb_dump.vcd
$date
	Sun Nov 15 20:54:57 2020
$end
$version
	Icarus Verilog
$end
$timescale
	1s
$end
$scope module tb $end
$var wire 4 ! num [3:0] $end
$var reg 1 " clock $end
$var reg 1 # reset $end
$scope module e1 $end
$var wire 1 " clock $end
$var wire 4 $ count_num [3:0] $end
$var wire 1 # reset $end
$var reg 4 % num [3:0] $end
$upscope $end
$upscope $end
$enddefinitions $end
#0
$dumpvars
b0 %
b0 $
0#
0"
b0 !
$end
#10
b10 !
b10 $
b10 %
1"
#20
0"
#30
b100 !
b100 $
b100 %
1"
#40
0"
#50
b110 !
b110 $
b110 %
1"
#60
0"
#70
b1000 !
b1000 $
b1000 %
1"
#80
0"
#90
b1010 !
b1010 $
b1010 %
1"
#100
0"
#110
b1100 !
b1100 $
b1100 %
1"
#120
0"
#130
b1110 !
b1110 $
b1110 %
1"
#140
0"
#150
b0 !
b0 $
b0 %
1"
#160
0"
#170
b10 !
b10 $
b10 %
1"
#180
0"
#190
b100 !
b100 $
b100 %
1"
#200
0"
#210
b110 !
b110 $
b110 %
1"
#220
0"
#230
b1000 !
b1000 $
b1000 %
1"
#240
0"
#250
b1010 !
b1010 $
b1010 %
1"
#260
0"
#270
b1100 !
b1100 $
b1100 %
1"
#280
0"
#290
b1110 !
b1110 $
b1110 %
1"
#300
0"
#310
b0 !
b0 $
b0 %
1"
1#
#320
0"
#330
b10 !
b10 $
b10 %
1"
0#
#340
0"
#350
b100 !
b100 $
b100 %
1"
#360
0"
#370
b110 !
b110 $
b110 %
1"
#380
0"
#390
b1000 !
b1000 $
b1000 %
1"
#400
0"
#410
b1010 !
b1010 $
b1010 %
1"
#420
0"
#430
b1100 !
b1100 $
b1100 %
1"
#440
0"
#450
b1110 !
b1110 $
b1110 %
1"
#460
0"
#470
b0 !
b0 $
b0 %
1"
#480
0"
#490
b10 !
b10 $
b10 %
1"
#500
0"
#510
b100 !
b100 $
b100 %
1"
#520
0"
#530
b110 !
b110 $
b110 %
1"
#540
0"
#550
b1000 !
b1000 $
b1000 %
1"
#560
0"
#570
b1010 !
b1010 $
b1010 %
1"
#580
0"
#590
b1100 !
b1100 $
b1100 %
1"
#600
0"
#610
b1110 !
b1110 $
b1110 %
1"
#620
0"
#630
b0 !
b0 $
b0 %
1"
#640
0"
#650
b10 !
b10 $
b10 %
1"
#660
0"
#670
b100 !
b100 $
b100 %
1"
#680
0"
#690
b110 !
b110 $
b110 %
1"
#700
0"
#710
b1000 !
b1000 $
b1000 %
1"
#720
0"
#730
b1010 !
b1010 $
b1010 %
1"
#740
0"
#750
b1100 !
b1100 $
b1100 %
1"
#760
0"
#770
b1110 !
b1110 $
b1110 %
1"
#780
0"
#790
b0 !
b0 $
b0 %
1"
#800
0"
#810
b10 !
b10 $
b10 %
1"
#820
0"
#830
b100 !
b100 $
b100 %
1"
#840
0"
#850
b110 !
b110 $
b110 %
1"
#860
0"
#870
b1000 !
b1000 $
b1000 %
1"
#880
0"
#890
b1010 !
b1010 $
b1010 %
1"
